alpyne/__init__.py
alpyne/constants.py
alpyne/data.py
alpyne/env.py
alpyne/errors.py
alpyne/outputs.py
alpyne/sim.py
alpyne/spaces.py
alpyne/typing.py
alpyne/utils.py
alpyne/resources/alpyne-1.2.0.jar
alpyne/resources/alpyne_lib/aopalliance-repackaged-3.0.1.jar
alpyne/resources/alpyne_lib/classmate-1.5.1.jar
alpyne/resources/alpyne_lib/commons-cli-1.5.0.jar
alpyne/resources/alpyne_lib/grizzly-framework-3.0.0.jar
alpyne/resources/alpyne_lib/grizzly-http-3.0.0.jar
alpyne/resources/alpyne_lib/grizzly-http-server-3.0.0.jar
alpyne/resources/alpyne_lib/hk2-api-3.0.1.jar
alpyne/resources/alpyne_lib/hk2-locator-3.0.1.jar
alpyne/resources/alpyne_lib/hk2-utils-3.0.1.jar
alpyne/resources/alpyne_lib/itu-1.7.0.jar
alpyne/resources/alpyne_lib/jackson-annotations-2.12.2.jar
alpyne/resources/alpyne_lib/jackson-core-2.14.2.jar
alpyne/resources/alpyne_lib/jackson-databind-2.14.2.jar
alpyne/resources/alpyne_lib/jackson-dataformat-yaml-2.15.2.jar
alpyne/resources/alpyne_lib/jackson-module-jaxb-annotations-2.12.2.jar
alpyne/resources/alpyne_lib/jakarta.activation-api-2.0.1.jar
alpyne/resources/alpyne_lib/jakarta.annotation-api-2.0.0.jar
alpyne/resources/alpyne_lib/jakarta.inject-api-2.0.0.jar
alpyne/resources/alpyne_lib/jakarta.validation-api-3.0.0.jar
alpyne/resources/alpyne_lib/jakarta.ws.rs-api-3.0.0.jar
alpyne/resources/alpyne_lib/javassist-3.25.0-GA.jar
alpyne/resources/alpyne_lib/javax.activation-api-1.2.0.jar
alpyne/resources/alpyne_lib/jaxb-api-2.3.1.jar
alpyne/resources/alpyne_lib/jersey-client-3.0.2.jar
alpyne/resources/alpyne_lib/jersey-common-3.0.2.jar
alpyne/resources/alpyne_lib/jersey-container-grizzly2-http-3.0.2.jar
alpyne/resources/alpyne_lib/jersey-entity-filtering-3.0.2.jar
alpyne/resources/alpyne_lib/jersey-hk2-3.0.2.jar
alpyne/resources/alpyne_lib/jersey-media-json-jackson-3.0.2.jar
alpyne/resources/alpyne_lib/jersey-server-3.0.2.jar
alpyne/resources/alpyne_lib/json-schema-validator-1.0.87.jar
alpyne/resources/alpyne_lib/jsonschema-generator-4.31.1.jar
anylogic_alpyne-1.2.1.dist-info/LICENSE
anylogic_alpyne-1.2.1.dist-info/METADATA
anylogic_alpyne-1.2.1.dist-info/WHEEL
anylogic_alpyne-1.2.1.dist-info/top_level.txt
anylogic_alpyne-1.2.1.dist-info/RECORD
