Metadata-Version: 2.1
Name: anylogic-alpyne
Version: 1.2.1
Summary: Run AnyLogic models exported from the RL Experiment
Home-page: https://github.com/the-anylogic-company/Alpyne
Author: AnyLogic
Author-email: info@anylogic.com
Classifier: Development Status :: 4 - Beta
Classifier: Programming Language :: Python :: 3
Classifier: Operating System :: OS Independent
Classifier: License :: OSI Approved :: MIT License
Requires-Python: >=3.10
License-File: LICENSE
Requires-Dist: gymnasium
Requires-Dist: numpy
Requires-Dist: psutil
Requires-Dist: requests
Provides-Extra: examples
Requires-Dist: pandas; extra == "examples"
Requires-Dist: bayesian-optimization; extra == "examples"
Requires-Dist: stable-baselines3; extra == "examples"
Requires-Dist: openpyxl; extra == "examples"
Requires-Dist: tabulate; extra == "examples"
